fps_spacex/__init__.py
fps_spacex/main.py
fps_spacex/routes.py
fps_spacex/static/htmx.min.js
fps_spacex/static/tailwindcss.min.js
fps_spacex/templates/create_environment.html
fps_spacex/templates/create_server.html
fps_spacex/templates/edit_environment.html
fps_spacex/templates/edit_server.html
fps_spacex/templates/environment.html
fps_spacex/templates/environments.html
fps_spacex/templates/index.html
fps_spacex/templates/search_environments.html
fps_spacex/templates/searched_environments.html
fps_spacex/templates/server.html
fps_spacex/templates/servers.html
fps_spacex-0.0.4.dist-info/METADATA
fps_spacex-0.0.4.dist-info/WHEEL
fps_spacex-0.0.4.dist-info/entry_points.txt
fps_spacex-0.0.4.dist-info/licenses/LICENSE.txt
fps_spacex-0.0.4.dist-info/RECORD
